migrark/__init__.py
migrark/api.py
migrark/collector/__init__.py
migrark/collector/collector.py
migrark/collector/directory_collector.py
migrark/collector/memory_collector.py
migrark/connection/__init__.py
migrark/connection/connection.py
migrark/migrator.py
migrark/models/__init__.py
migrark/models/migration.py
migrark/versioner/__init__.py
migrark/versioner/memory_versioner.py
migrark/versioner/sql_versioner.py
migrark/versioner/versioner.py
migrark-0.6.0.dist-info/LICENSE
migrark-0.6.0.dist-info/WHEEL
migrark-0.6.0.dist-info/METADATA
migrark-0.6.0.dist-info/RECORD
