Metadata-Version: 2.1
Name: migrark
Version: 0.6.0
Summary: Migration Management Library
License: MIT
Author: Esteban Echeverry
Author-email: eecheverry@nubark.com
Requires-Python: >=3.8,<4.0
Classifier: License :: OSI Approved :: MIT License
Classifier: Programming Language :: Python :: 3
Classifier: Programming Language :: Python :: 3.8
